discrete_key_value_bottleneck_pytorch/__init__.py
discrete_key_value_bottleneck_pytorch/discrete_key_value_bottleneck.py
discrete_key_value_bottleneck_pytorch-0.1.1.dist-info/LICENSE
discrete_key_value_bottleneck_pytorch-0.1.1.dist-info/METADATA
discrete_key_value_bottleneck_pytorch-0.1.1.dist-info/WHEEL
discrete_key_value_bottleneck_pytorch-0.1.1.dist-info/top_level.txt
discrete_key_value_bottleneck_pytorch-0.1.1.dist-info/RECORD
