Metadata-Version: 2.1
Name: discrete-key-value-bottleneck-pytorch
Version: 0.1.1
Summary: Discrete Key / Value Bottleneck - Pytorch
Home-page: https://github.com/lucidrains/discrete-key-value-bottleneck-pytorch
Author: Phil Wang
Author-email: lucidrains@gmail.com
License: MIT
Keywords: artificial intelligence,deep learning,quantization,memory,transfer learning
Classifier: Development Status :: 4 - Beta
Classifier: Intended Audience :: Developers
Classifier: Topic :: Scientific/Engineering :: Artificial Intelligence
Classifier: License :: OSI Approved :: MIT License
Classifier: Programming Language :: Python :: 3.6
License-File: LICENSE
Requires-Dist: einops (>=0.6)
Requires-Dist: vector-quantize-pytorch (>=1.6.28)
Requires-Dist: torch (>=1.6)
